netbox_loadbalancer/__init__.py
netbox_loadbalancer/admin.py
netbox_loadbalancer/filtersets.py
netbox_loadbalancer/forms.py
netbox_loadbalancer/models.py
netbox_loadbalancer/navigation.py
netbox_loadbalancer/search.py
netbox_loadbalancer/tables.py
netbox_loadbalancer/template_content.py
netbox_loadbalancer/urls.py
netbox_loadbalancer/views.py
netbox_loadbalancer/api/__init__.py
netbox_loadbalancer/api/serializers.py
netbox_loadbalancer/api/urls.py
netbox_loadbalancer/api/views.py
netbox_loadbalancer/migrations/0001_initial.py
netbox_loadbalancer/migrations/__init__.py
netbox_loadbalancer/templates/netbox_loadbalancer/f5cluster.html
netbox_loadbalancer/templates/netbox_loadbalancer/f5cluster.html.bak
netbox_loadbalancer/templates/netbox_loadbalancer/f5pool.html
netbox_loadbalancer/templates/netbox_loadbalancer/f5pool_delete_nodes.html
netbox_loadbalancer/templates/netbox_loadbalancer/f5pool_update_nodes.html
netbox_loadbalancer/templates/netbox_loadbalancer/f5poolnode.html
netbox_loadbalancer/templates/netbox_loadbalancer/f5poolnode_edit.html
netbox_loadbalancer/templates/netbox_loadbalancer/f5virtualserver.html
netbox_loadbalancer/templates/netbox_loadbalancer/f5virtualserver_delete_pools.html
netbox_loadbalancer/templates/netbox_loadbalancer/f5virtualserver_update_pools.html
netbox_loadbalancer/templates/netbox_loadbalancer/inc/f5devicecluster_info.html
netbox_loadbalancer/templates/netbox_loadbalancer/inc/f5poolnode_info.html
netbox_loadbalancer/templates/netbox_loadbalancer_tab_view/cluster_devices.html
netbox_loadbalancer/templates/netbox_loadbalancer_tab_view/cluster_nodes.html
netbox_loadbalancer/templates/netbox_loadbalancer_tab_view/cluster_pools.html
netbox_loadbalancer/templates/netbox_loadbalancer_tab_view/cluster_tab_base.html
netbox_loadbalancer/templates/netbox_loadbalancer_tab_view/cluster_vips.html
netbox_loadbalancer/templates/netbox_loadbalancer_tab_view/cluster_virtualdevices.html
netbox_loadbalancer-1.0.1.dist-info/LICENSE
netbox_loadbalancer-1.0.1.dist-info/METADATA
netbox_loadbalancer-1.0.1.dist-info/WHEEL
netbox_loadbalancer-1.0.1.dist-info/entry_points.txt
netbox_loadbalancer-1.0.1.dist-info/top_level.txt
netbox_loadbalancer-1.0.1.dist-info/RECORD
