Metadata-Version: 2.1
Name: netbox-loadbalancer
Version: 1.0.1
Summary: Manager LoadBalancer with Netbox
Author: HuyTM
License: Apache 2.0
License-File: LICENSE
